oarepo_doi/__init__.py
oarepo_doi/api.py
oarepo_doi/doi_mapping_base.py
oarepo_doi/ext.py
oarepo_doi/actions/__init__.py
oarepo_doi/actions/doi.py
oarepo_doi/services/__init__.py
oarepo_doi/services/components/__init__.py
oarepo_doi/translations/messages.pot
oarepo_doi/translations/cs/LC_MESSAGES/messages.mo
oarepo_doi/translations/cs/LC_MESSAGES/messages.po
oarepo_doi/translations/en/LC_MESSAGES/messages.mo
oarepo_doi/translations/en/LC_MESSAGES/messages.po
oarepo_doi/types/__init__.py
oarepo_doi/types/doi.py
oarepo_doi_tmp-1.0.22.dist-info/licenses/LICENSE
oarepo_doi_tmp-1.0.22.dist-info/METADATA
oarepo_doi_tmp-1.0.22.dist-info/WHEEL
oarepo_doi_tmp-1.0.22.dist-info/entry_points.txt
oarepo_doi_tmp-1.0.22.dist-info/top_level.txt
oarepo_doi_tmp-1.0.22.dist-info/RECORD
