Metadata-Version: 2.4
Name: oarepo-doi-tmp
Version: 1.0.22
License-File: LICENSE
Requires-Dist: invenio-requests
Requires-Dist: oarepo-requests
Provides-Extra: dev
Requires-Dist: oarepo-tools; extra == "dev"
Provides-Extra: tests
Requires-Dist: oarepo-model-builder-tests; extra == "tests"
Requires-Dist: oarepo-requests; extra == "tests"
Dynamic: license-file
